Metadata-Version: 1.1
Name: PHEnix
Version: 1.post4
Summary: Public Health England(UK) SNP calling pipeline tools.
Home-page: https://github.com/phe-bioinformatics/PHEnix
Author: Public Health England
Author-email: NGSSBioinformatics@phe.gov.uk
License: UNKNOWN
Download-URL: https://github.com/phe-bioinformatics/PHEnix/archive/1-4-1.tar.gz
Platform: UNKNOWN
